amc2moodle/__init__.py
amc2moodle/_version.py
amc2moodle/amc2moodle/README.md
amc2moodle/amc2moodle/__init__.py
amc2moodle/amc2moodle/amc2moodle_class.py
amc2moodle/amc2moodle/automultiplechoice.sty.ltxml
amc2moodle/amc2moodle/convert.py
amc2moodle/amc2moodle/fp.sty.ltxml
amc2moodle/amc2moodle/mhchem.sty.ltxml
amc2moodle/amc2moodle/transform.xslt
amc2moodle/amc2moodle/transform2html.xslt
amc2moodle/amc2moodle/transform_ns.xslt
amc2moodle/amc2moodle/transform_qtype.xslt
amc2moodle/amc2moodle/bin/amc2moodle.py
amc2moodle/moodle2amc/README.md
amc2moodle/moodle2amc/__init__.py
amc2moodle/moodle2amc/_questions.py
amc2moodle/moodle2amc/_quiz.py
amc2moodle/moodle2amc/html2tex.xslt
amc2moodle/moodle2amc/struc2tex.xslt
amc2moodle/moodle2amc/bin/moodle2amc.py
amc2moodle/tests/__init__.py
amc2moodle/tests/test_amc2moodle.py
amc2moodle/tests/test_moodle2amc.py
amc2moodle/tests/test_utils_calculatedParser.py
amc2moodle/tests/test_utils_text.py
amc2moodle/tests/payload_test_amc2moodle/4.png
amc2moodle/tests/payload_test_amc2moodle/QCM.pdf
amc2moodle/tests/payload_test_amc2moodle/QCM.tex
amc2moodle/tests/payload_test_amc2moodle/QCM.xml
amc2moodle/tests/payload_test_amc2moodle/QCM_wo-tikz.tex
amc2moodle/tests/payload_test_amc2moodle/QCM_wo-tikz.xml
amc2moodle/tests/payload_test_amc2moodle/cleaning.tex
amc2moodle/tests/payload_test_amc2moodle/cleaning.xml
amc2moodle/tests/payload_test_amc2moodle/common-bank.tex
amc2moodle/tests/payload_test_amc2moodle/element.tex
amc2moodle/tests/payload_test_amc2moodle/includestyles.tex
amc2moodle/tests/payload_test_amc2moodle/numerical.tex
amc2moodle/tests/payload_test_amc2moodle/numerical.xml
amc2moodle/tests/payload_test_amc2moodle/tikz.tex
amc2moodle/tests/payload_test_amc2moodle/Figures/tinymonk.pdf
amc2moodle/tests/payload_test_amc2moodle/Figures/other/4r.png
amc2moodle/tests/payload_test_amc2moodle/Figures/other/schema_interpL.png
amc2moodle/tests/payload_test_moodle2amc/automultiplechoice.sty
amc2moodle-2.12.1.dist-info/METADATA
amc2moodle-2.12.1.dist-info/WHEEL
amc2moodle-2.12.1.dist-info/entry_points.txt
amc2moodle-2.12.1.dist-info/licenses/LICENSE
amc2moodle-2.12.1.dist-info/RECORD
