Metadata-Version: 2.4
Name: amc2moodle
Version: 2.12.1
Summary: A tool to convert automultiplechoice quizz to moodle questions
Project-URL: Homepage, https://github.com/nennigb/amc2moodle
Project-URL: Repository, https://github.com/nennigb/amc2moodle
Project-URL: Issues, https://github.com/nennigb/amc2moodle/issues
Author-email: "B. Nennig" <benoit.nennig@isae-supmeca.fr>, "L. Laurent" <luc.laurent@lecnam.net>
License:                     GNU GENERAL PUBLIC LICENSE
License-File: LICENSE
Classifier: License :: OSI Approved :: GNU General Public License v3 (GPLv3)
Classifier: Operating System :: OS Independent
Classifier: Programming Language :: Python :: 3
Requires-Python: >=3.8
Requires-Dist: lxml>=3.5.0
Requires-Dist: markdown
Requires-Dist: pyparsing>=2.4.6
Requires-Dist: wand>=0.5.9
Requires-Dist: wheel>=0.29.0
Provides-Extra: test
Requires-Dist: pytest; extra == 'test'
Requires-Dist: pytest-cov[all]; extra == 'test'
